{
  "approval_lookup": "required",
  "audit_lookup": "required",
  "authorization_lookup": "required",
  "decision": "DEFINED",
  "evidence_boundary": {
    "evidence_only": true,
    "no_connector_mutations": true,
    "no_credential_creation": true,
    "no_external_actions": true,
    "no_external_api_calls": true,
    "no_production_activation": true
  },
  "fail_closed_conditions": [
    "state_missing",
    "approval_missing",
    "authorization_missing",
    "audit_linkage_missing",
    "registry_unavailable"
  ],
  "gateway_decision_flow": [
    "load connector state",
    "validate state exists",
    "load approvals",
    "load authorization",
    "load audit linkage",
    "allow only if AUTHORIZED and all checks pass",
    "otherwise BLOCK"
  ],
  "generated_files": [
    "governance/evidence/pb105/governance_enforcement_gateway.json",
    "governance/evidence/pb105/governance_enforcement_gateway_summary.md",
    "governance/evidence/pb105/generated_commit_title.txt",
    "governance/evidence/pb105/generated_pr_title.txt",
    "governance/evidence/pb105/generated_pr_body.md"
  ],
  "generated_pr_body": "## PURPOSE\nPB-105 defines the runtime gateway that checks state, approval, authorization, and audit records before connector execution.\n\n## RISK\nA runtime gateway without registry lookups could allow execution from stale or missing governance state.\n\n## POLICY LINK\nAGENTS.md fail-closed, audit-first engineering, backend truth source-of-truth, human oversight, rollback and forensics, and trust-state isolation rules. PB-102 Governance Approval Workflow, PB-103 Governance Review Execution Framework, and PB-104 Governance State Registry.\n\n## REQUIRED APPROVALS\nUSBAY-AUDIT and USBAY-GLOBAL23 review are required before merge. This PB does not authorize production activation, external API calls, credential creation, connector mutation, or runtime deployment.\n\n## GOVERNANCE CHECKS\nJSON evidence must parse. Generated metadata, source evidence references, required runtime controls, fail-closed conditions, audit linkage, state validation, and required PR sections must validate.\n\n## AUDIT\nPB-105 generates governance_enforcement_gateway.json and summary evidence.\n\n## IMPACT\nUSBAY gains a gateway definition while runtime deployment remains blocked.\n\n## Decision\nVERIFIED\n\n## Status\nREADY_FOR_REVIEW\n",
  "generated_pr_metadata": {
    "branch_name": "governance/governance-enforcement-gateway",
    "commit_title": "PB-105 VERIFIED: Governance Enforcement Gateway",
    "decision": "VERIFIED",
    "pr_title": "PB-105 VERIFIED: Governance Enforcement Gateway",
    "status": "READY_FOR_REVIEW"
  },
  "json_file": "governance_enforcement_gateway.json",
  "pb": "PB-105",
  "production_activation": false,
  "runtime_implementation_present": false,
  "source_evidence": [
    "governance/evidence/pb102/governance_approval_workflow.json",
    "governance/evidence/pb103/governance_review_execution_framework.json",
    "governance/evidence/pb104/governance_state_registry.json"
  ],
  "state_lookup": "required",
  "status": "READY_FOR_REVIEW",
  "summary_file": "governance_enforcement_gateway_summary.md",
  "title": "Governance Enforcement Gateway"
}
